gopylink/__init__.py
gopylink/registry.py
gopylink-1.0.2.dist-info/licenses/LICENSE
gopylink-1.0.2.dist-info/METADATA
gopylink-1.0.2.dist-info/WHEEL
gopylink-1.0.2.dist-info/top_level.txt
gopylink-1.0.2.dist-info/RECORD
