Metadata-Version: 2.4
Name: gopylink
Version: 1.0.2
Summary: Call Go from Python and call Python from Go, simply.
Author-email: WeiminWang <wang0.618@qq.com>
License-Expression: MIT
Project-URL: Homepage, https://github.com/ray4go/GoPyLink
Requires-Python: >=3.7
License-File: LICENSE
Requires-Dist: goray>=1.2.0
Dynamic: license-file
